esgsegfseghjsejhgsghjejhsejgjshe/__init__.py
esgsegfseghjsejhgsghjejhsejgjshe-1.0.0.dist-info/METADATA
esgsegfseghjsejhgsghjejhsejgjshe-1.0.0.dist-info/WHEEL
esgsegfseghjsejhgsghjejhsejgjshe-1.0.0.dist-info/top_level.txt
esgsegfseghjsejhgsghjejhsejgjshe-1.0.0.dist-info/RECORD
